setup.py
mphatoday.egg-info/PKG-INFO
mphatoday.egg-info/SOURCES.txt
mphatoday.egg-info/dependency_links.txt
mphatoday.egg-info/requires.txt
mphatoday.egg-info/top_level.txt
sunnyday/__init__.py
sunnyday/sunnyday.py