Metadata-Version: 2.1
Name: mphatoday
Version: 1.0.0
Summary: weather app, pulls data from api
Author: Mpatisi
Author-email: mphatomnz@gmail.com
License: MIT
Keywords: weather,forecast
Classifier: Development Status :: 3 - Alpha
Classifier: Intended Audience :: Developers
Classifier: Topic :: Software Development :: Build Tools
Classifier: License :: OSI Approved :: MIT License
Classifier: Programming Language :: Python :: 3.5
Classifier: Programming Language :: Python :: 3.6
Classifier: Programming Language :: Python :: 3.7
